{
  "data": {
    "source": "campaign-design/CAMDEV-8",
    "id": 1,
    "author": "system:jira",
    "data": {
      "payload": {
        "audienceSegments": "Segmentación",
        "campaignId": "CAMDEV-8",
        "campaignName": "Nombre de campaña",
        "campaignShortName": "Nombre Corto de Campaña",
        "campaignStatus": "Online",
        "campaignType": "Activación",
        "challengeEndDate": "2025-12-15",
        "comercialDetail": "* Detalle comercial1\n* Detalle comercial2\n* Detalle comercial3\n* Detalle comercial4\n* Detalle comercial5",
        "description": "NUEVO CAMBIO DE DESCRIPCION",
        "descriptionShort": "Descripcion breve 2",
        "endDate": "2024-12-07",
        "externalCampaignId": "9",
        "idRecompensa": "Descripcion breve 2",
        "images": {
          "binderImg": "campaign-dsg-media/images/CAMDEV-8",
          "bucketImg": "s3-dev-io-made-campaign-dsg-media-01",
          "internal": "internal.png",
          "preview": "preview.png"
        },
        "minSpend": "Descripcion breve 2",
        "minTransactions": "All",
        "notes": "Notas adicionales",
        "notificationChannels": ["Email", "Push"],
        "rewardAmount": "Descripcion breve 2",
        "rewardDate": "2025-01-03",
        "rewardPercentaje": "All",
        "rewardType": "Sorteo",
        "scope": "All",
        "shortCodeCampaign": "Descripcion breve 2",
        "startDate": "2024-12-06",
        "targetAudience": "Customer",
        "termsAndConditions": "Terminos y Condiciones",
        "transactionType": ["Email", "Push"],
        "updatedAt": "2025-03-14T16:36:49.922Z"
      },
      "snapshot": {
        "audienceSegments": "Segmentación",
        "campaignId": "CAMDEV-8",
        "campaignName": "Te premiamos por tus compras",
        "campaignShortName": "Nombre Corto de Campaña",
        "campaignStatus": "Online",
        "campaignType": "Activación",
        "challengeEndDate": "2025-12-15",
        "comercialDetail": "* Detalle comercial1\n* Detalle comercial2\n* Detalle comercial3\n* Detalle comercial4\n* Detalle comercial5",
        "createdAt": "2024-12-06T22:38:34.617Z",
        "description": "version2",
        "descriptionShort": "Descripcion breve 2",
        "endDate": "2024-12-07",
        "externalCampaignId": "9",
        "idRecompensa": "212",
        "images": {
          "binderImg": "campaign-dsg-media/images/CAMDEV-8",
          "bucketImg": "s3-dev-io-made-campaign-dsg-media-01",
          "internal": "internal.png",
          "preview": "preview.png"
        },
        "maxRewardAmount": "400",
        "minSpend": "1200",
        "minTransactions": "10",
        "notes": "Notas adicionales",
        "notificationChannels": ["Email", "Push"],
        "rewardAmount": "500",
        "rewardDate": "2025-01-03",
        "rewardPercentaje": "20",
        "rewardType": "Sorteo",
        "scope": "All",
        "shortCodeCampaign": "Descripcion breve 2",
        "startDate": "2024-12-06",
        "targetAudience": "Customer",
        "termsAndConditions": "Terminos y Condiciones",
        "transactionType": ["Email", "Push"],
        "updatedAt": "2025-03-14T16:36:49.922Z"
      }
    },
    "dataContentType": "application/json",
    "dataEncodingType": "identity",
    "time": 1741970209922,
    "transaction": "d775ae1f-ff69-4419-b1db-776407a3ad60",
    "type": "pe.io.made.campaign-design.updated.v1"
  },
  "topic": "pe.io.made.campaign-design.updated.v1"
}
